{
    "$schema": "https://github.com/tago-io/tagoio-cli/blob/master/docs/schema.json",
    "analysisPath": "./src/analysis",
    "buildPath": "./build",
    "prod": {
        "analysisList": [
            {
                "fileName": "alert-handler.ts",
                "name": "[TagoIO] - Alert Handler",
                "id": "65d652b77bbc1a00097e6038"
            },
            {
                "fileName": "alert-trigger.ts",
                "name": "[TagoIO] - Alert Trigger",
                "id": "65d652b52b1f97001014b1f8"
            },
            {
                "fileName": "battery-updater.ts",
                "name": "[TagoIO] - Battery Updater",
                "id": "65d652b2f6a78100097c5f3e"
            },
            {
                "fileName": "data-retention.ts",
                "name": "[TagoIO] - Data Retention Updater",
                "id": "65d652b0ac58b700109ec8ac"
            },
            {
                "fileName": "handler.ts",
                "name": "[TagoIO] - Handler",
                "id": "65d652ae23cbe20011ac8fcc"
            },
            {
                "fileName": "monthly-usage-reset.ts",
                "name": "[TagoIO] - Monthly Usage Reset",
                "id": "65d652ab69d97d0011da4e3d"
            },
            {
                "fileName": "send-report.ts",
                "name": "[TagoIO] - Send Report ",
                "id": "65d652a97bbc1a00097e5f0f"
            },
            {
                "fileName": "status-updater.ts",
                "name": "[TagoIO] - Status Updater",
                "id": "65d652a62b1f97001014b11e"
            },
            {
                "fileName": "uplink-handler.ts",
                "name": "[TagoIO] - Uplink Handler",
                "id": "65d652a41a0da200085493b9"
            },
            {
                "fileName": "user-sign-up.ts",
                "name": "[TagoIO] - User Signup",
                "id": "65d652a15129c1000fb88685"
            }
        ],
        "id": "65390a60d0a3ed00097690ed",
        "profileName": "Arendsee",
        "email": "markjov@gmail.com"
    }
}